pybus/__init__.py
pybus/base/__init__.py
pybus/base/dispatcher.py
pybus/base/maps.py
pybus/base/engine/__init__.py
pybus/base/engine/events.py
pybus/base/engine/requests.py
pybus/base/handlers/__init__.py
pybus/base/handlers/abstract.py
pybus/base/handlers/wrapper.py
pybus/base/routers/__init__.py
pybus/base/routers/eventrouter.py
pybus/base/routers/messagerouter.py
pybus/base/routers/requestrouter.py
pybus/core/__init__.py
pybus/core/exceptions.py
pybus/core/helpers.py
pybus/core/types.py
pybus/core/api/__init__.py
pybus/core/api/broker.py
pybus/core/api/dispatcher.py
pybus/core/api/engine.py
pybus/core/api/handlers.py
pybus/core/api/maps.py
pybus/core/api/other.py
pybus/core/api/routers.py
pybus/core/api/typing.py
pybus/core/dependency/__init__.py
pybus/core/dependency/providers.py
pybus/core/inspection/__init__.py
pybus/core/inspection/sig.py
pybus/core/inspection/utils.py
async_py_bus-0.1.6.dist-info/METADATA
async_py_bus-0.1.6.dist-info/WHEEL
async_py_bus-0.1.6.dist-info/entry_points.txt
async_py_bus-0.1.6.dist-info/licenses/MITLicense
async_py_bus-0.1.6.dist-info/RECORD
