Metadata-Version: 2.4
Name: async-py-bus
Version: 0.1.6
Summary: Async message bus framework designed for event-driven, cqrs python projects
Project-URL: Repository, https://github.com/andrei-samofalov/async-py-bus
Project-URL: Issues, https://github.com/andrei-samofalov/async-py-bus/issues
Author-email: Andrei Samofalov <andrei.e.samofalov@gmail.com>
Maintainer-email: Andrei Samofalov <andrei.e.samofalov@gmail.com>
License-File: MITLicense
Keywords: async,bus,cqrs,edd,python
Requires-Python: >=3.11
